odoo/addons/account_fiscal_position_autodetect_optional_vies/README.rst
odoo/addons/account_fiscal_position_autodetect_optional_vies/__init__.py
odoo/addons/account_fiscal_position_autodetect_optional_vies/__manifest__.py
odoo/addons/account_fiscal_position_autodetect_optional_vies/i18n/account_fiscal_position_autodetect_optional_vies.pot
odoo/addons/account_fiscal_position_autodetect_optional_vies/models/__init__.py
odoo/addons/account_fiscal_position_autodetect_optional_vies/models/account_fiscal_position.py
odoo/addons/account_fiscal_position_autodetect_optional_vies/readme/CONFIGURE.rst
odoo/addons/account_fiscal_position_autodetect_optional_vies/readme/CONTRIBUTORS.rst
odoo/addons/account_fiscal_position_autodetect_optional_vies/readme/DESCRIPTION.rst
odoo/addons/account_fiscal_position_autodetect_optional_vies/readme/USAGE.rst
odoo/addons/account_fiscal_position_autodetect_optional_vies/static/description/icon.png
odoo/addons/account_fiscal_position_autodetect_optional_vies/static/description/index.html
odoo/addons/account_fiscal_position_autodetect_optional_vies/tests/__init__.py
odoo/addons/account_fiscal_position_autodetect_optional_vies/tests/test_account_fiscal_position_vies.py
odoo/addons/account_fiscal_position_autodetect_optional_vies/views/account_fiscal_position_view.xml
odoo13_addon_account_fiscal_position_autodetect_optional_vies-13.0.1.0.2.dist-info/METADATA
odoo13_addon_account_fiscal_position_autodetect_optional_vies-13.0.1.0.2.dist-info/WHEEL
odoo13_addon_account_fiscal_position_autodetect_optional_vies-13.0.1.0.2.dist-info/top_level.txt
odoo13_addon_account_fiscal_position_autodetect_optional_vies-13.0.1.0.2.dist-info/RECORD
